Metadata-Version: 1.1
Name: distelli
Version: 0.1.0
Summary: Client for Distelli REST API https://www.distelli.com/docs/api/
Home-page: https://github.com/maxpeterson/distelli-python/
Author: UNKNOWN
Author-email: UNKNOWN
License: UNKNOWN
Platform: UNKNOWN
Classifier: Intended Audience :: Developers
Classifier: License :: OSI Approved :: BSD License
Classifier: Operating System :: OS Independent
Classifier: Programming Language :: Python
